TwitterAdsWindsorApi/__init__.py
TwitterAdsWindsorApi/client.py
TwitterAdsWindsorApi/enums.py
test/__init__.py
test/tests.py
TwitterAdsWindsorApi-1.0.6.dist-info/METADATA
TwitterAdsWindsorApi-1.0.6.dist-info/WHEEL
TwitterAdsWindsorApi-1.0.6.dist-info/top_level.txt
TwitterAdsWindsorApi-1.0.6.dist-info/RECORD
