Metadata-Version: 2.1
Name: TwitterAdsWindsorApi
Version: 1.0.6
Summary: Easy access to windsor.ai Twitter Ads APIs
Home-page: https://github.com/windsor-ai/TwitterAdsWindsorApi
Author: Windsor AI
Author-email: dev@windsor.ai
Requires-Dist: requests (~=2.25.1)
